{
  "config": {
    "N": 64,
    "n": 16,
    "num_records": 311,
    "record_dim": 16,
    "model_types": [
      "dot",
      "decision_tree",
      "neural_network"
    ],
    "policy_size": 8,
    "num_runs": 1,
    "save_results": true,
    "results_dir": "experiments/results/scheme1_ccs23"
  },
  "models": {
    "dot": {
      "encrypt_times": [
        0.0
      ],
      "query_times": [
        0.0003206999972462654
      ],
      "decrypt_times": [
        0
      ],
      "communication_sizes": [
        46077,
        271,
        2815
      ],
      "comm_upload_sizes": [
        46077
      ],
      "comm_query_sizes": [
        271
      ],
      "comm_decrypt_sizes": [
        2815
      ],
      "runs": [
        {
          "run_id": 0,
          "query_time": 0.0003206999972462654,
          "decrypt_time": 0,
          "success": true,
          "num_results": 311
        }
      ]
    },
    "decision_tree": {
      "encrypt_times": [
        0.0
      ],
      "query_times": [
        0.00010439998004585505
      ],
      "decrypt_times": [
        0
      ],
      "communication_sizes": [
        46077,
        266,
        2815
      ],
      "comm_upload_sizes": [
        46077
      ],
      "comm_query_sizes": [
        266
      ],
      "comm_decrypt_sizes": [
        2815
      ],
      "runs": [
        {
          "run_id": 0,
          "query_time": 0.00010439998004585505,
          "decrypt_time": 0,
          "success": true,
          "num_results": 311
        }
      ]
    },
    "neural_network": {
      "encrypt_times": [
        0.0
      ],
      "query_times": [
        0.003340600000228733
      ],
      "decrypt_times": [
        0
      ],
      "communication_sizes": [
        46077,
        1723,
        2815
      ],
      "comm_upload_sizes": [
        46077
      ],
      "comm_query_sizes": [
        1723
      ],
      "comm_decrypt_sizes": [
        2815
      ],
      "runs": [
        {
          "run_id": 0,
          "query_time": 0.003340600000228733,
          "decrypt_time": 0,
          "success": true,
          "num_results": 311
        }
      ]
    }
  },
  "summary": {
    "dot": {
      "avg_encrypt_time": 0.0,
      "std_encrypt_time": 0.0,
      "min_encrypt_time": 0.0,
      "max_encrypt_time": 0.0,
      "avg_query_time": 0.0003206999972462654,
      "std_query_time": 0.0,
      "min_query_time": 0.0003206999972462654,
      "max_query_time": 0.0003206999972462654,
      "avg_decrypt_time": 0.0,
      "std_decrypt_time": 0.0,
      "min_decrypt_time": 0.0,
      "max_decrypt_time": 0.0,
      "avg_communication_size": 16.003580729166668,
      "std_communication_size": 20.526565850937335,
      "total_communication": 48.0107421875
    },
    "decision_tree": {
      "avg_encrypt_time": 0.0,
      "std_encrypt_time": 0.0,
      "min_encrypt_time": 0.0,
      "max_encrypt_time": 0.0,
      "avg_query_time": 0.00010439998004585505,
      "std_query_time": 0.0,
      "min_query_time": 0.00010439998004585505,
      "max_query_time": 0.00010439998004585505,
      "avg_decrypt_time": 0.0,
      "std_decrypt_time": 0.0,
      "min_decrypt_time": 0.0,
      "max_decrypt_time": 0.0,
      "avg_communication_size": 16.001953125,
      "std_communication_size": 20.527813922447052,
      "total_communication": 48.005859375
    },
    "neural_network": {
      "avg_encrypt_time": 0.0,
      "std_encrypt_time": 0.0,
      "min_encrypt_time": 0.0,
      "max_encrypt_time": 0.0,
      "avg_query_time": 0.003340600000228733,
      "std_query_time": 0.0,
      "min_query_time": 0.003340600000228733,
      "max_query_time": 0.003340600000228733,
      "avg_decrypt_time": 0.0,
      "std_decrypt_time": 0.0,
      "min_decrypt_time": 0.0,
      "max_decrypt_time": 0.0,
      "avg_communication_size": 16.476236979166668,
      "std_communication_size": 20.1719732317448,
      "total_communication": 49.4287109375
    }
  }
}