{
  "config": {
    "N": 64,
    "n": 16,
    "num_records": 170,
    "record_dim": 256,
    "model_types": [
      "dot",
      "decision_tree",
      "neural_network"
    ],
    "policy_size": 8,
    "num_runs": 1,
    "save_results": true,
    "results_dir": "experiments/results/scheme1_ccs23"
  },
  "models": {
    "dot": {
      "encrypt_times": [
        0.0
      ],
      "query_times": [
        0.0017365999519824982
      ],
      "decrypt_times": [
        0
      ],
      "communication_sizes": [
        392454,
        2431,
        1546
      ],
      "comm_upload_sizes": [
        392454
      ],
      "comm_query_sizes": [
        2431
      ],
      "comm_decrypt_sizes": [
        1546
      ],
      "runs": [
        {
          "run_id": 0,
          "query_time": 0.0017365999519824982,
          "decrypt_time": 0,
          "success": true,
          "num_results": 170
        }
      ]
    },
    "decision_tree": {
      "encrypt_times": [
        0.0
      ],
      "query_times": [
        7.740000728517771e-05
      ],
      "decrypt_times": [
        0
      ],
      "communication_sizes": [
        392454,
        266,
        1546
      ],
      "comm_upload_sizes": [
        392454
      ],
      "comm_query_sizes": [
        266
      ],
      "comm_decrypt_sizes": [
        1546
      ],
      "runs": [
        {
          "run_id": 0,
          "query_time": 7.740000728517771e-05,
          "decrypt_time": 0,
          "success": true,
          "num_results": 170
        }
      ]
    },
    "neural_network": {
      "encrypt_times": [
        0.0
      ],
      "query_times": [
        0.004817200009711087
      ],
      "decrypt_times": [
        0
      ],
      "communication_sizes": [
        392454,
        4784,
        1546
      ],
      "comm_upload_sizes": [
        392454
      ],
      "comm_query_sizes": [
        4784
      ],
      "comm_decrypt_sizes": [
        1546
      ],
      "runs": [
        {
          "run_id": 0,
          "query_time": 0.004817200009711087,
          "decrypt_time": 0,
          "success": true,
          "num_results": 170
        }
      ]
    }
  },
  "summary": {
    "dot": {
      "avg_encrypt_time": 0.0,
      "std_encrypt_time": 0.0,
      "min_encrypt_time": 0.0,
      "max_encrypt_time": 0.0,
      "avg_query_time": 0.0017365999519824982,
      "std_query_time": 0.0,
      "min_query_time": 0.0017365999519824982,
      "max_query_time": 0.0017365999519824982,
      "avg_decrypt_time": 0.0,
      "std_decrypt_time": 0.0,
      "min_decrypt_time": 0.0,
      "max_decrypt_time": 0.0,
      "avg_communication_size": 129.04654947916666,
      "std_communication_size": 179.7534731489742,
      "total_communication": 387.1396484375
    },
    "decision_tree": {
      "avg_encrypt_time": 0.0,
      "std_encrypt_time": 0.0,
      "min_encrypt_time": 0.0,
      "max_encrypt_time": 0.0,
      "avg_query_time": 7.740000728517771e-05,
      "std_query_time": 0.0,
      "min_query_time": 7.740000728517771e-05,
      "max_query_time": 7.740000728517771e-05,
      "avg_decrypt_time": 0.0,
      "std_decrypt_time": 0.0,
      "min_decrypt_time": 0.0,
      "max_decrypt_time": 0.0,
      "avg_communication_size": 128.341796875,
      "std_communication_size": 180.25218458258314,
      "total_communication": 385.025390625
    },
    "neural_network": {
      "avg_encrypt_time": 0.0,
      "std_encrypt_time": 0.0,
      "min_encrypt_time": 0.0,
      "max_encrypt_time": 0.0,
      "avg_query_time": 0.004817200009711087,
      "std_query_time": 0.0,
      "min_query_time": 0.004817200009711087,
      "max_query_time": 0.004817200009711087,
      "avg_decrypt_time": 0.0,
      "std_decrypt_time": 0.0,
      "min_decrypt_time": 0.0,
      "max_decrypt_time": 0.0,
      "avg_communication_size": 129.8125,
      "std_communication_size": 179.2161675042906,
      "total_communication": 389.4375
    }
  }
}